{
   "home": "Home",
   "company": "公司專業投資者",
   "institution": "金融機構專業投資者",
   "person": "個人專業投資者",
   "t0": "關於申購基金所需文件和流程",
   "t1": "基金申購書（下载填写）",
   "t2": "關於公司和金融機構的區別",
   "t3": "KYC及開戶文件（下載填寫）",
   "b0": "填妥文件，掃描版請郵寄 XXXXX。客戶部會核對內容，確認後可交正本於XXXX",
   "person_1": "證明文件（KYC相關）",
   "person_2": "有效身份證明文件",
   "person_3": "有效的住址證明 ( 3个月內簽發)",
   "person_4": "港幣8,000,000元資產證明",
   "person_5": "聲明文件（KYC相關）",
   "person_6": "W8-BEN 表格",
   "person_7": "投資者風險分析問卷",
   "person_8": "個人專業投資者聲明",
   "person_9": "開戶文件（開戶相關）",
   "person_10": "客戶資料表格",
   "person_11": "打包档（個人專業投資者）",
   "person_link_1": "https://media.artatechfin.com/AAML/Individual-PI/1.%20AAML%20CLIENT%20INFORMATION%20STATEMENT%20%E5%AE%A2%E6%88%B6%E8%B3%87%E6%96%99%E8%A1%A8.pdf",
   "person_link_2": "https://media.artatechfin.com/AAML/Individual-PI/3.%20W-8BEN.pdf",
   "person_link_3": "https://media.artatechfin.com/AAML/Individual-PI/4.%20AAML%20Investor%20Risk%20Profiling%20Questionnaire%20-%20%E6%8A%95%E8%B3%87%E9%A2%A8%E9%9A%AA%E8%A9%95%E4%BC%B0%E5%95%8F%E5%88%B8.pdf",
   "person_link_4": "https://media.artatechfin.com/AAML/Individual-PI/5.%20AAML%20Individual%20Professional%20Investor%20Declaration%20%E5%80%8B%E4%BA%BA%E5%B0%88%E6%A5%AD%E6%8A%95%E8%B3%87%E8%80%85%E8%81%B2%E6%98%8E%E6%9B%B8.pdf",
   "person_link_5": "https://media.artatechfin.com/AAML/Individual-PI/Individual-PI.zip",
   "company_1": "證明文件（KYC相關）",
   "company_2": "商業登記證或同等證書",
   "company_3": "更改公司秘書及董事通知書（如適用）",
   "company_4": "職權證明書（最近6個月內）或同等證書",
   "company_5": "公司註冊證書",
   "company_6": "公司章程大綱、組織細則或類似證明）",
   "company_7": "業務地址證明（最近3個月內）",
   "company_8": "公司擁有權及控制權架構表",
   "company_9": "（適用于多於一層擁有權之公司）",
   "company_10": "所有主要股東，董事，授權人士及擔保人之身份證或護照",
   "company_11": "所有董事，授權交易人士有效地址證明（最近3個月內）",
   "company_12": "批准開立戶口的董事會決議（ 附樣本）",
   "company_13": "資產證明",
   "company_14": "詳細說明公司實體的公司結構，投資流程和控制機制的證明文件",
   "company_15": "最新之財政審計報告（如適用）",
   "company_16": "銀行帳戶證明",
   "company_17": "聲明文件（KYC相關）",
   "company_18": "W-8BEN-E 表格",
   "company_19": "自我證明表格 — 實體",
   "company_20": "自我證明表格 — 控權人（每名主要股東，董事及授權人士，各簽一份）",
   "company_21": "專業投資者評估表格（如適用）",
   "company_22": "開戶文件（開戶相關）",
   "company_23": "公司賬戶開戶表",
   "company_24": "打包檔（公司專業投資者）",
   "end":""
}